{
  "skill_id": "RSF-IRC-016",
  "domain": "industrial-robot-control",
  "domain_en": "Industrial Robot Control",
  "internal_uri": "urn:rsf:skill:irc-0016",
  "esco_uri": null,
  "preferred_label_ko": "생산 라인 로봇 운용",
  "preferred_label_en": "Production Line Robot Operation",
  "description_ko": "실제 제조 환경에서 로봇 운용",
  "description_en": "Operate robots in actual manufacturing environment",
  "skill_type": "competence",
  "proficiency_level": 3,
  "role_mapping": ["operator", "engineer"],
  "parent_skill_id": "RSF-IRC-006",
  "related_skills": [
    {
      "target": "RSF-IRC-006",
      "type": "specialization",
      "weight": 1,
      "source": "heuristic"
    },
    {
      "target": "RSF-IRC-015",
      "type": "co_required",
      "weight": 0.7,
      "source": "heuristic"
    },
    {
      "target": "RSF-IRC-017",
      "type": "co_required",
      "weight": 0.7,
      "source": "heuristic"
    }
  ],
  "esco_broader": null,
  "smartfactory_context": "현장 검증: 생산 라인 로봇 운용 수행 능력 입증"
}
